component_changelog/__init__.py
component_changelog/py.typed
component_changelog/schemas.py
component_changelog-0.2.3.dist-info/METADATA
component_changelog-0.2.3.dist-info/WHEEL
component_changelog-0.2.3.dist-info/RECORD
