Metadata-Version: 2.1
Name: component-changelog
Version: 0.2.3
Summary: 
Author: Galileo Technologies, Inc.
Author-email: team@rungalileo.io
Requires-Python: >=3.9,<4.0
Classifier: Programming Language :: Python :: 3
Classifier: Programming Language :: Python :: 3.9
Classifier: Programming Language :: Python :: 3.10
Classifier: Programming Language :: Python :: 3.11
Classifier: Programming Language :: Python :: 3.12
Requires-Dist: packaging (>=24.2,<25.0)
Requires-Dist: pydantic (>=2.10.5,<3.0.0)
